ineware/__init__.py
ineware/dataset_class.py
ineware-0.0.4.dist-info/LICENSE.md
ineware-0.0.4.dist-info/METADATA
ineware-0.0.4.dist-info/WHEEL
ineware-0.0.4.dist-info/top_level.txt
ineware-0.0.4.dist-info/RECORD
