Metadata-Version: 2.1
Name: ineware
Version: 0.0.4
Summary: A light weight Python library for INE API json-stat
Home-page: https://github.com/rgameroe/ineware
Author: Roberto Gamero
Author-email: rgameroe@alumnos.unex.es
License: MIT
Platform: UNKNOWN
Classifier: Intended Audience :: Science/Research
Classifier: License :: OSI Approved :: MIT License
Classifier: Operating System :: OS Independent
Classifier: Programming Language :: Python :: 3
Classifier: Programming Language :: Python :: 3.4
Classifier: Programming Language :: Python :: 3.5
Classifier: Programming Language :: Python :: 3.9
License-File: LICENSE.md
Requires-Dist: requests (>=2.25.1)
